pyintelbras/__init__.py
pyintelbras/api.py
pyintelbras/exceptions.py
pyintelbras/helpers.py
pyintelbras-0.0.33.dist-info/LICENSE
pyintelbras-0.0.33.dist-info/METADATA
pyintelbras-0.0.33.dist-info/WHEEL
pyintelbras-0.0.33.dist-info/top_level.txt
pyintelbras-0.0.33.dist-info/RECORD
